{
    "_links": {
        "self": {
            "href": "http:\/\/documents\/taxonomy\/term\/14?_format=hal_json"
        },
        "type": {
            "href": "http:\/\/drupal.org\/rest\/type\/taxonomy_term\/mt_product_tags"
        }
    },
    "tid": [
        {
            "value": 14
        }
    ],
    "uuid": [
        {
            "value": "c3aabfb7-7853-4b2d-89d2-0c89f4497165"
        }
    ],
    "langcode": [
        {
            "value": "en",
            "lang": "en"
        }
    ],
    "vid": [
        {
            "target_id": "mt_product_tags"
        }
    ],
    "name": [
        {
            "value": "Product Tag 1",
            "lang": "en"
        }
    ],
    "weight": [
        {
            "value": 0
        }
    ],
    "changed": [
        {
            "value": "2016-06-09T10:04:48+00:00",
            "lang": "en",
            "format": "Y-m-d\\TH:i:sP"
        }
    ],
    "default_langcode": [
        {
            "value": true,
            "lang": "en"
        }
    ],
    "path": [
        {
            "alias": null,
            "pid": null,
            "langcode": "en",
            "lang": "en"
        }
    ]
}