{
    "_links": {
        "self": {
            "href": "http:\/\/default\/taxonomy\/term\/23?_format=hal_json"
        },
        "type": {
            "href": "http:\/\/drupal.org\/rest\/type\/taxonomy_term\/pds_code_profile_access_type"
        },
        "http:\/\/drupal.org\/rest\/relation\/taxonomy_term\/pds_code_profile_access_type\/parent": [
            null
        ]
    },
    "tid": [
        {
            "value": 23
        }
    ],
    "uuid": [
        {
            "value": "5ee655ed-a7fb-4d65-9b00-e32d926ac383"
        }
    ],
    "langcode": [
        {
            "value": "en",
            "lang": "en"
        }
    ],
    "vid": [
        {
            "target_id": "pds_code_profile_access_type"
        }
    ],
    "status": [
        {
            "value": true,
            "lang": "en"
        }
    ],
    "name": [
        {
            "value": "Sign",
            "lang": "en"
        }
    ],
    "weight": [
        {
            "value": 2
        }
    ],
    "_embedded": {
        "http:\/\/drupal.org\/rest\/relation\/taxonomy_term\/pds_code_profile_access_type\/parent": [
            null
        ]
    },
    "changed": [
        {
            "value": "2018-10-16T17:29:23+00:00",
            "lang": "en",
            "format": "Y-m-d\\TH:i:sP"
        }
    ],
    "default_langcode": [
        {
            "value": true,
            "lang": "en"
        }
    ],
    "metatag": [
        {
            "value": {
                "title": "Sign | pds193",
                "canonical_url": "http:\/\/default\/taxonomy\/term\/23"
            }
        }
    ],
    "field_pds_code_text_value": [
        {
            "value": "S",
            "lang": "en"
        }
    ]
}